st_circular_progress/__init__.py
st_circular_progress/frontend/build/asset-manifest.json
st_circular_progress/frontend/build/bootstrap.min.css
st_circular_progress/frontend/build/index.html
st_circular_progress/frontend/build/progress.css
st_circular_progress/frontend/build/static/js/main.a9466aa5.js
st_circular_progress/frontend/build/static/js/main.a9466aa5.js.LICENSE.txt
st_circular_progress/frontend/build/static/js/main.a9466aa5.js.map
st_circular_progress-0.3.9.dist-info/LICENSE
st_circular_progress-0.3.9.dist-info/METADATA
st_circular_progress-0.3.9.dist-info/WHEEL
st_circular_progress-0.3.9.dist-info/top_level.txt
st_circular_progress-0.3.9.dist-info/RECORD
