Metadata-Version: 2.1
Name: st_circular_progress
Version: 0.3.9
Summary: Circular progress wheel for Streamlit
Home-page: https://github.com/sqlinsights/st-circular-progress
Author: Carlos D Serrano
Author-email: sqlinsights@gmail.com
Requires-Python: >=3.6
License-File: LICENSE
